quatorch/__init__.py
quatorch/quaternion.py
quatorch-0.2.0.dist-info/WHEEL
quatorch-0.2.0.dist-info/METADATA
quatorch-0.2.0.dist-info/RECORD
