Metadata-Version: 2.4
Name: quatorch
Version: 0.2.0
Summary: Quaternion operations in pure PyTorch
Keywords: quaternion,rotation,3d,orientation,pytorch
Author: Lucas N. Egidio
Author-email: Lucas N. Egidio <lucasegidio1@gmail.com>
License-Expression: MIT
Classifier: Development Status :: 5 - Production/Stable
Classifier: Intended Audience :: Science/Research
Classifier: Topic :: Scientific/Engineering :: Mathematics
Classifier: Topic :: Scientific/Engineering :: Physics
Classifier: Programming Language :: Python :: 3
Requires-Dist: torch>=1.7.0
Requires-Dist: torch ; extra == 'cpu'
Requires-Dist: torch ; extra == 'cu128'
Maintainer: Lucas N. Egidio
Maintainer-email: Lucas N. Egidio <lucasegidio1@gmail.com>
Requires-Python: >=3.10
Project-URL: Documentation, https://egidioln.github.io/QuaTorch/
Project-URL: Homepage, https://github.com/egidioln/QuaTorch/
Project-URL: Issues, https://github.com/egidioln/QuaTorch/issues
Project-URL: Repository, https://github.com/egidioln/QuaTorch.git
Provides-Extra: cpu
Provides-Extra: cu128
